{
  "formatVersion": "1.1",
  "component": {
    "group": "io.github.luiinge",
    "module": "jexten-gradle-plugin",
    "version": "1.0.0",
    "attributes": {
      "org.gradle.status": "release"
    }
  },
  "createdBy": {
    "gradle": {
      "version": "8.1"
    }
  },
  "variants": [
    {
      "name": "apiElements",
      "attributes": {
        "org.gradle.category": "library",
        "org.gradle.dependency.bundling": "external",
        "org.gradle.jvm.version": 19,
        "org.gradle.libraryelements": "jar",
        "org.gradle.usage": "java-api"
      },
      "dependencies": [
        {
          "group": "io.github.luiinge",
          "module": "jexten",
          "version": {
            "requires": "1.0.0"
          }
        }
      ],
      "files": [
        {
          "name": "jexten-gradle-plugin-1.0.0.jar",
          "url": "jexten-gradle-plugin-1.0.0.jar",
          "size": 39808,
          "sha512": "724968bc77a7bdfe9466a065c75f0013117928dbc8414c1e9a80f1cbec5133daf607b60ccc243b817e576abf22817fef58189c8a7e01c87033e74870c4eaf86f",
          "sha256": "210b4c25fe87747647f36d67c69f91603f248291289a64a7c8301223bc909eb0",
          "sha1": "5842d0b499708a22618d2fa20cbcaf270b6a7e86",
          "md5": "31aa67652f3d9f55d8561989af18bb06"
        }
      ]
    },
    {
      "name": "runtimeElements",
      "attributes": {
        "org.gradle.category": "library",
        "org.gradle.dependency.bundling": "external",
        "org.gradle.jvm.version": 19,
        "org.gradle.libraryelements": "jar",
        "org.gradle.usage": "java-runtime"
      },
      "dependencies": [
        {
          "group": "io.github.luiinge",
          "module": "jexten",
          "version": {
            "requires": "1.0.0"
          }
        }
      ],
      "files": [
        {
          "name": "jexten-gradle-plugin-1.0.0.jar",
          "url": "jexten-gradle-plugin-1.0.0.jar",
          "size": 39808,
          "sha512": "724968bc77a7bdfe9466a065c75f0013117928dbc8414c1e9a80f1cbec5133daf607b60ccc243b817e576abf22817fef58189c8a7e01c87033e74870c4eaf86f",
          "sha256": "210b4c25fe87747647f36d67c69f91603f248291289a64a7c8301223bc909eb0",
          "sha1": "5842d0b499708a22618d2fa20cbcaf270b6a7e86",
          "md5": "31aa67652f3d9f55d8561989af18bb06"
        }
      ]
    }
  ]
}
